__init__.py
config.py
server.py
trino_client.py
mcp_trino_python-0.6.0.dist-info/licenses/LICENSE
mcp_trino_python-0.6.0.dist-info/METADATA
mcp_trino_python-0.6.0.dist-info/WHEEL
mcp_trino_python-0.6.0.dist-info/top_level.txt
mcp_trino_python-0.6.0.dist-info/RECORD
