Metadata-Version: 2.4
Name: mcp-trino-python
Version: 0.6.0
Summary: A Model Context Protocol (MCP) connector for Trino, enabling seamless integration between MCP-compliant services and Trino query engine
License: Apache-2.0
Keywords: trino,connector,mcp
Classifier: Programming Language :: Python :: 3.12
Classifier: License :: OSI Approved :: Apache Software License
Classifier: Operating System :: OS Independent
Classifier: Development Status :: 4 - Beta
Classifier: Intended Audience :: Developers
Classifier: Topic :: Software Development :: Libraries :: Python Modules
Requires-Python: >=3.12
License-File: LICENSE
Requires-Dist: fastapi>=0.115.12
Requires-Dist: loguru>=0.7.3
Requires-Dist: mcp[cli]>=1.6.0
Requires-Dist: python-dotenv>=1.1.0
Requires-Dist: trino>=0.333.0
Dynamic: license-file
